smart_pdf/__init__.py
smart_pdf/smart_pdf.py
smart_pdf-2023.9.11.1.dist-info/LICENSE
smart_pdf-2023.9.11.1.dist-info/METADATA
smart_pdf-2023.9.11.1.dist-info/WHEEL
smart_pdf-2023.9.11.1.dist-info/top_level.txt
smart_pdf-2023.9.11.1.dist-info/zip-safe
smart_pdf-2023.9.11.1.dist-info/RECORD
