Metadata-Version: 2.1
Name: smart-pdf
Version: 2023.9.11.1
Summary: SmartPDF: AI powered pdf reader.
Home-page: UNKNOWN
Author: Sergei Belousov aka BeS
Author-email: sergei.o.belousov@gmail.com
License: UNKNOWN
Platform: UNKNOWN
Classifier: Programming Language :: Python :: 3
License-File: LICENSE
Requires-Dist: openai (==0.27.6)
Requires-Dist: langchain (==0.0.285)
Requires-Dist: pypdf (==3.16.0)
Requires-Dist: tiktoken (==0.4.0)
Requires-Dist: faiss-cpu (==1.7.3)
